agz/__init__.py
agz/encryption.py
agz/rubika.py
agz/socket.py
agz/url.py
agz/Configs/__init__.py
agz-3.0.9.dist-info/LICENSE
agz-3.0.9.dist-info/METADATA
agz-3.0.9.dist-info/WHEEL
agz-3.0.9.dist-info/top_level.txt
agz-3.0.9.dist-info/RECORD
