Metadata-Version: 2.1
Name: agz
Version: 3.0.9
Summary: This is fastest library for deploying robots on Rubika accounts.
Home-page: https://github.com/aliexers
Author: Ali Ganji zadeh
Author-email: yb.windows.plus@gmail.com
Keywords: agz,agz lib,agz-lib,library,rubikalib,rubika,bot,robot
Classifier: Programming Language :: Python :: 3.7
Classifier: Programming Language :: Python :: 3.8
Classifier: Programming Language :: Python :: 3.9
Classifier: Programming Language :: Python :: 3.10
Classifier: Programming Language :: Python :: 3.11
Classifier: License :: OSI Approved :: MIT License
Classifier: Topic :: Internet
Classifier: Topic :: Communications
Classifier: Topic :: Communications :: Chat
Classifier: Topic :: Software Development :: Libraries
Classifier: Topic :: Software Development :: Libraries :: Python Modules
Classifier: Topic :: Software Development :: Libraries :: Application Frameworks
Requires-Python: ~=3.7
License-File: LICENSE
Requires-Dist: requests
Requires-Dist: colorama
Requires-Dist: pycryptodome
Requires-Dist: urllib3
Requires-Dist: websocket-client
